{"v": {"$in": ["0.22.0", "0.22.1"]}, "$not": {"$or": [{"$not": {"$or": [{"$not": {"type": {"$in": ["zig", "br.exit", "uniq"]}}}, {"type": "zig", "lvl": {"$in": ["7", "14", "21", "27"]}}]}}, {"$not": {"$or": [{"name": "Midpoint", "start": "20260401171334S"}, {"name": "RoGGa", "char": "GrEE"}, {"name": "SlowGraham", "char": "GrEE"}, {"name": "Pigkeeper", "char": "GrEE"}, {"name": "Blyxx", "char": "GrEE"}, {"name": "demonstrator", "char": "GrEE"}, {"name": "happinesssam", "char": "GrEE"}, {"name": "TomBombadil", "char": "GrEE"}, {"name": "TCC", "char": "GrEE"}, {"name": "nojaa", "char": "GrEE"}, {"name": "Bronksi", "char": "GrEE"}, {"name": "Syis", "char": "GrEE"}, {"name": "Jannitor", "char": "GrEE"}, {"name": "kuniqs", "char": "GrEE"}, {"name": "Colgate", "char": "GrEE"}, {"name": "GameOver", "char": "GrEE"}, {"name": "dreamdao", "char": "GrEE"}, {"name": "ereinion", "char": "GrEE"}, {"name": "erikjake", "char": "GrEE"}, {"name": "particleface", "char": "GrEE"}, {"name": "kkplay", "char": "GrEE"}, {"name": "Strat", "char": "GrEE"}, {"name": "JolietJake", "char": "GrEE"}, {"name": "Larett", "char": "GrEE"}, {"name": "Hsik", "char": "GrEE"}, {"name": "Esekla", "char": "GrEE"}, {"name": "community", "char": "GrEE"}, {"name": "PieDemon", "char": "GrEE"}, {"name": "agentchuck", "char": "GrEE"}, {"name": "TheMeInTeam", "char": "GrEE"}, {"name": "quinnr", "char": "GrEE"}, {"name": "mdonais", "char": "GrEE"}, {"name": "zewo", "char": "GrEE"}, {"name": "Astinus", "char": "GrEE"}, {"name": "Zeldest", "char": "GrEE"}, {"name": "TheBenjamin", "char": "GrEE"}, {"name": "ContrarianOrange", "char": "GrEE"}, {"name": "Platt", "char": "GrEE"}, {"name": "Snarg", "char": "GrEE"}, {"name": "tmt", "char": "GrEE"}, {"name": "BeansWater", "char": "GrEE"}, {"name": "MrsPlatt", "char": "GrEE"}, {"name": "AquaGlass", "char": "GrEE"}, {"name": "dakkaduck", "char": "GrEE"}, {"name": "DevastatorOne", "char": "GrEE"}, {"name": "Hans", "char": "GrEE"}, {"name": "Dwargi", "char": "GrEE"}, {"name": "Endy73", "char": "GrEE"}, {"name": "Gobbopathe", "char": "GrEE"}, {"name": "jt", "char": "GrEE"}, {"name": "mobilemanners", "char": "GrEE"}, {"name": "Arcadio", "char": "GrEE"}, {"name": "Fougere", "char": "GrEE"}, {"name": "IjonTichy1", "char": "GrEE"}, {"name": "lontrex", "char": "GrEE"}, {"name": "Masnef", "char": "GrEE"}, {"name": "InabaYap", "char": "GrEE"}, {"name": "Aka8171", "char": "GrEE"}, {"name": "planckenstein", "char": "GrEE"}, {"name": "goupaloupa", "char": "GrEE"}, {"name": "Archion", "char": "GrEE"}, {"name": "EugeneJudo", "char": "GrEE"}, {"name": "abclol0070", "char": "GrEE"}, {"name": "ASCIIPhilia", "char": "GrEE"}, {"name": "DWEMPhilia", "char": "GrEE"}, {"name": "Caterwaul", "char": "GrEE"}, {"name": "Draconius", "char": "GrEE"}, {"name": "yakattack", "char": "GrEE"}, {"name": "enarc13", "char": "GrEE"}, {"name": "Abbadon", "char": "GrEE"}, {"name": "ElricMelnibone", "char": "GrEE"}, {"name": "brinewave", "char": "GrEE"}, {"name": "kickassninja", "char": "GrEE"}, {"name": "cpf86", "char": "GrEE"}, {"name": "Mariano", "char": "GrEE"}, {"name": "QuizMaster", "char": "GrEE"}, {"name": "krsz", "char": "GrEE"}, {"name": "Procrustes", "char": "GrEE"}, {"name": "justinlove", "char": "GrEE"}, {"name": "Scalebane", "char": "GrEE"}, {"name": "jaccarmac", "char": "GrEE"}, {"name": "tish", "char": "GrEE"}, {"name": "tyria", "char": "GrEE"}, {"name": "drwombats", "char": "GrEE"}, {"name": "Booper", "char": "GrEE"}, {"name": "LadyLuck", "char": "GrEE"}, {"name": "K8SM8S", "char": "GrEE"}, {"name": "Disease", "char": "GrEE"}, {"name": "ousd", "char": "GrEE"}, {"name": "SpideyBoy", "char": "GrEE"}, {"name": "SuperSimple", "char": "GrEE"}, {"name": "AshKetchup", "char": "GrEE"}, {"name": "PidgeonPower", "char": "GrEE"}, {"name": "Spatula", "char": "GrEE"}, {"name": "CallieX", "char": "GrEE"}, {"name": "CoolPlay", "char": "GrEE"}, {"name": "LottaHair", "char": "GrEE"}, {"name": "Notte", "char": "GrEE"}, {"name": "Vivy", "char": "GrEE"}, {"name": "playerghost", "char": "GrEE"}, {"name": "person50605", "char": "GrEE"}]}}]}}